django_pyoidc/VERSION
django_pyoidc/__init__.py
django_pyoidc/admin.py
django_pyoidc/apps.py
django_pyoidc/client.py
django_pyoidc/engine.py
django_pyoidc/exceptions.py
django_pyoidc/helper.py
django_pyoidc/models.py
django_pyoidc/py.typed
django_pyoidc/session.py
django_pyoidc/settings.py
django_pyoidc/utils.py
django_pyoidc/views.py
django_pyoidc/drf/__init__.py
django_pyoidc/drf/authentication.py
django_pyoidc/drf/schema.py
django_pyoidc/migrations/0001_initial.py
django_pyoidc/migrations/__init__.py
django_pyoidc/providers/__init__.py
django_pyoidc/providers/keycloak.py
django_pyoidc/providers/keycloak_10.py
django_pyoidc/providers/keycloak_17.py
django_pyoidc/providers/keycloak_18.py
django_pyoidc/providers/lemonldapng.py
django_pyoidc/providers/lemonldapng2.py
django_pyoidc/providers/provider.py
django_pyoidc-1.0.9.dist-info/METADATA
django_pyoidc-1.0.9.dist-info/WHEEL
django_pyoidc-1.0.9.dist-info/licenses/LICENSE
django_pyoidc-1.0.9.dist-info/RECORD
