Metadata-Version: 2.4
Name: django-pyoidc
Version: 1.0.9
Summary: Authenticate your users using OpenID Connect (OIDC)
Project-URL: repository, https://github.com/makinacorpus/django_pyoidc
Author-email: "Régis Leroy (Makina Corpus)" <django_pyoidc@makina-corpus.net>, "Paul Florence (Makina Corpus)" <django_pyoidc@makina-corpus.net>
License-Expression: GPL-3.0-only
License-File: LICENSE
Keywords: authentication,django,oidc,openid,openid-connect,single-sign-on,sso
Classifier: Development Status :: 5 - Production/Stable
Classifier: Environment :: Web Environment
Classifier: Framework :: Django
Classifier: Framework :: Django :: 4.2
Classifier: Framework :: Django :: 5
Classifier: Framework :: Django :: 5.0
Classifier: Framework :: Django :: 5.1
Classifier: Framework :: Django :: 5.2
Classifier: Framework :: Django :: 6.0
Classifier: Intended Audience :: Developers
Classifier: Natural Language :: English
Classifier: Operating System :: OS Independent
Classifier: Programming Language :: Python :: 3 :: Only
Classifier: Programming Language :: Python :: 3.8
Classifier: Programming Language :: Python :: 3.9
Classifier: Programming Language :: Python :: 3.10
Classifier: Programming Language :: Python :: 3.11
Classifier: Programming Language :: Python :: 3.12
Classifier: Programming Language :: Python :: 3.13
Classifier: Programming Language :: Python :: 3.14
Classifier: Topic :: Security
Classifier: Topic :: Utilities
Requires-Python: >=3.8
Requires-Dist: django>=3.2
Requires-Dist: jsonpickle
Requires-Dist: oic==1.7.0
Requires-Dist: pycryptodomex
Requires-Dist: pyjwt
Provides-Extra: drf
Requires-Dist: djangorestframework; extra == 'drf'
Requires-Dist: drf-spectacular; extra == 'drf'
